{"t": "Chapter 325 FIRE PREVENTION", "p": "/us/nsn/menominee/legislature/code/II/325", "et": "container", "dj": "/us/nsn/menominee/legislature/code/index.json", "fh": "/us/nsn/menominee/legislature/code/II/325/index.full.html", "sc": " Part II, Chapter 325", "rp": "II|325", "sp": "library|Code of the Menominee Indian Tribe|II|325", "c": [{"t": "\u00a7 325-1 Outdoor burning restricted.", "p": "/us/nsn/menominee/legislature/code/II/325-1", "et": "section", "sc": " Part II, \u00a7 325-1", "rp": "II|\u00a7325-1", "sp": "library|Code of the Menominee Indian Tribe|II|325|325-1", "c": [{"t": "A.", "p": "/us/nsn/menominee/legislature/code/II/325-1#A.", "et": "para", "sc": "Part II, \u00a7 325-1A.", "rp": "II|\u00a7325-1|A.", "c": [{"t": "(1)", "p": "/us/nsn/menominee/legislature/code/II/325-1#A.(1)", "et": "para", "sc": "Part II, \u00a7 325-1A.(1)", "rp": "II|\u00a7325-1|A.|(1)", "x": "When a fire is set and designed solely for warming the person or cooking fo"}, {"t": "(2)", "p": "/us/nsn/menominee/legislature/code/II/325-1#A.(2)", "et": "para", "sc": "Part II, \u00a7 325-1A.(2)", "rp": "II|\u00a7325-1|A.|(2)", "x": "When the ground is snow covered."}], "x": "Within the exterior boundaries of the Menominee Nation, it shall be unlawfu"}, {"t": "B.", "p": "/us/nsn/menominee/legislature/code/II/325-1#B.", "et": "para", "sc": "Part II, \u00a7 325-1B.", "rp": "II|\u00a7325-1|B.", "x": "Any person who sets a fire solely for warming the person or cooking food sh"}]}, {"t": "\u00a7 325-2 Permit considerations.", "p": "/us/nsn/menominee/legislature/code/II/325-2", "et": "section", "sc": " Part II, \u00a7 325-2", "rp": "II|\u00a7325-2", "sp": "library|Code of the Menominee Indian Tribe|II|325|325-2"}, {"t": "\u00a7 325-3 Permit restrictions.", "p": "/us/nsn/menominee/legislature/code/II/325-3", "et": "section", "sc": " Part II, \u00a7 325-3", "rp": "II|\u00a7325-3", "sp": "library|Code of the Menominee Indian Tribe|II|325|325-3"}, {"t": "\u00a7 325-4 Special authority to restrict burning.", "p": "/us/nsn/menominee/legislature/code/II/325-4", "et": "section", "sc": " Part II, \u00a7 325-4", "rp": "II|\u00a7325-4", "sp": "library|Code of the Menominee Indian Tribe|II|325|325-4", "c": [{"t": "A.", "p": "/us/nsn/menominee/legislature/code/II/325-4#A.", "et": "para", "sc": "Part II, \u00a7 325-4A.", "rp": "II|\u00a7325-4|A.", "x": "An announcement in the Shawano newspaper."}, {"t": "B.", "p": "/us/nsn/menominee/legislature/code/II/325-4#B.", "et": "para", "sc": "Part II, \u00a7 325-4B.", "rp": "II|\u00a7325-4|B.", "x": "Posting of signs at predesignated locations within the exterior boundaries "}]}, {"t": "\u00a7 325-5 Negligent handling of materials which might cause forest fire; vehicles causing fire. [Added 7-12-1990]", "p": "/us/nsn/menominee/legislature/code/II/325-5", "et": "section", "sc": " Part II, \u00a7 325-5", "rp": "II|\u00a7325-5", "sp": "library|Code of the Menominee Indian Tribe|II|325|325-5"}, {"t": "\u00a7 325-6 Violations and penalties.", "p": "/us/nsn/menominee/legislature/code/II/325-6", "et": "section", "sc": " Part II, \u00a7 325-6", "rp": "II|\u00a7325-6", "sp": "library|Code of the Menominee Indian Tribe|II|325|325-6"}]}